td_kernel_dmvw/__init__.py
td_kernel_dmvw/matrix_operations.py
td_kernel_dmvw/td_kernel_dmvw.py
tests/__init__.py
tests/test_cell_grid_content.py
tests/test_matrix_content.py
tests/test_matrix_content_single.py
tests/test_matrix_shape.py
td_kernel_dmvw-0.1.0.dist-info/LICENSE
td_kernel_dmvw-0.1.0.dist-info/METADATA
td_kernel_dmvw-0.1.0.dist-info/WHEEL
td_kernel_dmvw-0.1.0.dist-info/top_level.txt
td_kernel_dmvw-0.1.0.dist-info/RECORD
