Metadata-Version: 2.1
Name: td-kernel-dmvw
Version: 0.1.0
Summary: This project provides an algorithm for calculating gas distribution maps.
Home-page: https://gitlab.com/smueller18/TDKernelDMVW
Author: Stephan Müller
License: UNKNOWN
Project-URL: Documentation, https://smueller18.gitlab.com/TDKernelDMVW/
Project-URL: Source, https://gitlab.com/smueller18/TDKernelDMVW
Project-URL: Tracker, https://gitlab.com/smueller18/TDKernelDMVW/issues
Platform: UNKNOWN
Classifier: Programming Language :: Python :: 3
Classifier: License :: OSI Approved :: MIT License
Classifier: Operating System :: OS Independent
Requires-Python: >=3.6
Requires-Dist: numpy (==1.19.4)
